HACKING.txt
LICENSE.txt
MANIFEST.in
NEWS.txt
README.rst
bootstrap.py
buildout.cfg
make_sdist_and_test.sh
setup.py
src/bp/__init__.py
src/bp.tagging.egg-info/PKG-INFO
src/bp.tagging.egg-info/SOURCES.txt
src/bp.tagging.egg-info/dependency_links.txt
src/bp.tagging.egg-info/entry_points.txt
src/bp.tagging.egg-info/namespace_packages.txt
src/bp.tagging.egg-info/not-zip-safe
src/bp.tagging.egg-info/requires.txt
src/bp.tagging.egg-info/top_level.txt
src/bp/tagging/__init__.py
src/bp/tagging/bp.tagging.cfg
src/bp/tagging/file.py
src/bp/tagging/preferences.py
src/bp/tagging/table.py