Metadata-Version: 1.0
Name: bp.tagging
Version: 0.3
Summary: Multimedia file tagging library
Home-page: http://github.com/disko/bp.tagging
Author: Andreas Kaiser
Author-email: disko@binary-punks.com
License: BSD
Keywords: mp3 mp4 id3
Platform: UNKNOWN
Classifier: Programming Language :: Python
Classifier: Development Status :: 2 - Pre-Alpha
Classifier: Environment :: Console
Classifier: Intended Audience :: End Users/Desktop
Classifier: License :: OSI Approved :: BSD License
Classifier: Operating System :: POSIX
Classifier: Topic :: Multimedia :: Sound/Audio
Classifier: Topic :: Utilities
